llama_index/callbacks/deepeval/__init__.py
llama_index/callbacks/deepeval/base.py
llama_index_callbacks_deepeval-0.4.1.dist-info/METADATA
llama_index_callbacks_deepeval-0.4.1.dist-info/WHEEL
llama_index_callbacks_deepeval-0.4.1.dist-info/licenses/LICENSE
llama_index_callbacks_deepeval-0.4.1.dist-info/RECORD
